dewew/__init__.py
dewew/tools.py
dewew-0.0.7.dist-info/licenses/LICENSE
dewew-0.0.7.dist-info/METADATA
dewew-0.0.7.dist-info/WHEEL
dewew-0.0.7.dist-info/top_level.txt
dewew-0.0.7.dist-info/RECORD
