Metadata-Version: 2.4
Name: dewew
Version: 0.0.7
Summary: GitHub fayllarini yuklovchi oddiy vosita.
Home-page: https://github.com/DeWeWO/uzb_kitoblar
Author: DeWeW
Author-email: dewel000per@gmail.com
License: MIT
Classifier: Programming Language :: Python :: 3
Classifier: Operating System :: OS Independent
Requires-Python: >=3.6
License-File: LICENSE
Requires-Dist: colorama
Requires-Dist: requests
Dynamic: author
Dynamic: author-email
Dynamic: classifier
Dynamic: description
Dynamic: description-content-type
Dynamic: home-page
Dynamic: license
Dynamic: license-file
Dynamic: requires-dist
Dynamic: requires-python
Dynamic: summary
